smarter_client/__init__.py
smarter_client/_consts.py
smarter_client/dict_util.py
smarter_client/version.py
smarter_client/domain/__init__.py
smarter_client/domain/identity_toolkit_client.py
smarter_client/domain/models.py
smarter_client/domain/smarter_client.py
smarter_client/domain/decorators/session.py
smarter_client/managed_devices/__init__.py
smarter_client/managed_devices/base.py
smarter_client/managed_devices/kettle_v3.py
smarter_client-0.2.4.dist-info/METADATA
smarter_client-0.2.4.dist-info/WHEEL
smarter_client-0.2.4.dist-info/licenses/LICENSE
smarter_client-0.2.4.dist-info/RECORD
