Metadata-Version: 2.3
Name: smarter-client
Version: 0.2.4
Summary: Smarter Kettle client library
Project-URL: Homepage, https://www.github.com/kbirger/smarter-kettle-client
Project-URL: Release Notes, https://www.github.com/kbirger/smarter-kettle-client
Project-URL: Source, https://www.github.com/kbirger/smarter-kettle-client
Author: @kbirger
Author-email: Kirill Birger <kbirger@gmail.com>
License: MIT
License-File: LICENSE
Keywords: smarter kettle python
Classifier: License :: OSI Approved :: MIT License
Classifier: Programming Language :: Python :: 3
Classifier: Programming Language :: Python :: 3.12
Requires-Python: >=3.12.4
Requires-Dist: aiohttp~=3.9
Requires-Dist: astroid~=3.1
Requires-Dist: pylint~=3.1
Requires-Dist: pyrebase-air>=4.9.1
Requires-Dist: setuptools>=69.5.1
